<?xml version="1.0" encoding="UTF-8" ?>
<!-- Copyright 2018 Joel Feldman, Andrew Rechnitzer and Elyse Yeager -->
<!-- This work is licensed under the Creative Commons Attribution-NonCommercial-ShareAlike 4.0 International License-->
<!-- https://creativecommons.org/licenses/by-nc-sa/4.0 -->

<subsection xmlns:xi="http://www.w3.org/2001/XInclude">
<title>Exercises</title>

<xi:include href="prob_s3.4.1.xml" />
<xi:include href="prob_s3.4.2.xml" />
<xi:include href="prob_s3.4.3.xml" />
<xi:include href="prob_s3.4.4.xml" />
<xi:include href="prob_s3.4.5.xml" />
<xi:include href="prob_s3.4.6.xml" />
<xi:include href="prob_s3.4.7.xml" />
<xi:include href="prob_s3.4.8.xml" />
<xi:include href="prob_s3.4.9.xml" />


</subsection>
